foo_et_al_parameterization/SphereVolume.py
foo_et_al_parameterization/__init__.py
foo_et_al_parameterization-0.0.10.dist-info/LICENSE
foo_et_al_parameterization-0.0.10.dist-info/METADATA
foo_et_al_parameterization-0.0.10.dist-info/WHEEL
foo_et_al_parameterization-0.0.10.dist-info/top_level.txt
foo_et_al_parameterization-0.0.10.dist-info/RECORD
