Metadata-Version: 2.1
Name: foo-et-al-parameterization
Version: 0.0.10
Summary: A basic python library to gain the volume of a sphere given its radius
Author-email: Aidan Goldstein <goldstai@oregonstate.edu>
Project-URL: Homepage, https://github.com/aidangold/foo-et-al-parameterization
Classifier: Programming Language :: Python :: 3
Classifier: License :: OSI Approved :: MIT License
Classifier: Operating System :: OS Independent
Requires-Python: >=3.8
License-File: LICENSE
